reddit_detective/__init__.py
reddit_detective/data_models.py
reddit_detective/exceptions.py
reddit_detective/karma.py
reddit_detective/network.py
reddit_detective/relationships.py
reddit_detective/utils.py
reddit_detective/analytics/__init__.py
reddit_detective/analytics/metrics.py
reddit_detective/analytics/utils.py
reddit_detective-0.1.4.dist-info/LICENSE
reddit_detective-0.1.4.dist-info/METADATA
reddit_detective-0.1.4.dist-info/WHEEL
reddit_detective-0.1.4.dist-info/top_level.txt
reddit_detective-0.1.4.dist-info/RECORD
