Metadata-Version: 2.1
Name: reddit-detective
Version: 0.1.4
Summary: Play detective on Reddit
Home-page: https://github.com/umitkaanusta/reddit-detective
Author: Ümit Kaan Usta
Author-email: u.kaanusta@gmail.com
License: MIT
Keywords: reddit,data,analysis,analytics,social,network,graph,neo4j,media,news,politics,campaign,information,troll,comment,influencer,idea,spread,campaign,elections
Platform: UNKNOWN
Classifier: Development Status :: 3 - Alpha
Classifier: License :: OSI Approved :: MIT License
Classifier: Intended Audience :: Science/Research
Classifier: Intended Audience :: Developers
Classifier: Intended Audience :: Education
Classifier: Topic :: Scientific/Engineering
Classifier: Topic :: Scientific/Engineering :: Information Analysis
Classifier: Topic :: Sociology
Classifier: Topic :: Education
Classifier: License :: OSI Approved :: MIT License
Classifier: Programming Language :: Python :: 3.6
Classifier: Programming Language :: Python :: 3.7
Classifier: Programming Language :: Python :: 3.8
Classifier: Programming Language :: Python :: 3.9
Requires-Python: >=3.6
Requires-Dist: praw
Requires-Dist: neo4j
